literategit/__init__.py
literategit/_version.py
literategit/cli/__init__.py
literategit/cli/dump_all_trees.py
literategit/cli/render.py
literategit/cli/repo_for_path.py
literategit/content.html.tmpl
literategit/diff.html.tmpl
literategit/dump_all_trees.py
literategit/example_create_url.py
literategit/literate-git.css
literategit/literate-git.js
literategit/node.html.tmpl
literategit/page.html.tmpl
literategit-0.5.1.dist-info/COPYING
literategit-0.5.1.dist-info/LICENCE.txt
literategit-0.5.1.dist-info/METADATA
literategit-0.5.1.dist-info/WHEEL
literategit-0.5.1.dist-info/entry_points.txt
literategit-0.5.1.dist-info/RECORD
